autoDiff/__init__.py
autoDiff/autoDiff.py
autoDiff/element_func.py
autoDiff/operator.py
autoDiff/optimization.py
tests/__init__.py
tests/test_autoDiff.py
tests/test_element_funcs.py
tests/test_operators.py
tests/test_optimization.py
AutoDiff_StanAndyJohn-0.1.1.dist-info/LICENSE
AutoDiff_StanAndyJohn-0.1.1.dist-info/METADATA
AutoDiff_StanAndyJohn-0.1.1.dist-info/WHEEL
AutoDiff_StanAndyJohn-0.1.1.dist-info/top_level.txt
AutoDiff_StanAndyJohn-0.1.1.dist-info/RECORD
