Metadata-Version: 2.1
Name: AutoDiff-StanAndyJohn
Version: 0.1.1
Summary: autodifferentiation package
Home-page: https://github.com/StanAndyJohn/cs207-FinalProject
Author: Harvard CS207 Group 33
Author-email: johnathan_jiang@harvard.edu
License: UNKNOWN
Platform: UNKNOWN
Classifier: Programming Language :: Python :: 3
Classifier: License :: OSI Approved :: MIT License
Classifier: Operating System :: OS Independent
Requires-Python: >=3.6
Requires-Dist: numpy (>=1.15.2)
Requires-Dist: pythonds (>=1.2.1)
Requires-Dist: pytest (>=3.4.2)
Requires-Dist: pytest-cov (>=2.5.1)
Requires-Dist: pytest-dependency (>=0.4)
Requires-Dist: matplotlib (==3.1.1)
